ncloud_cdn/__init__.py
ncloud_cdn/api_client.py
ncloud_cdn/configuration.py
ncloud_cdn/rest.py
ncloud_cdn/api/__init__.py
ncloud_cdn/api/v2_api.py
ncloud_cdn/model/__init__.py
ncloud_cdn/model/cdn_plus_instance.py
ncloud_cdn/model/cdn_plus_purge_history.py
ncloud_cdn/model/cdn_plus_rule.py
ncloud_cdn/model/cdn_plus_service_domain.py
ncloud_cdn/model/common_code.py
ncloud_cdn/model/get_cdn_plus_instance_list_request.py
ncloud_cdn/model/get_cdn_plus_instance_list_response.py
ncloud_cdn/model/get_cdn_plus_purge_history_list_request.py
ncloud_cdn/model/get_cdn_plus_purge_history_list_response.py
ncloud_cdn/model/get_global_cdn_instance_list_request.py
ncloud_cdn/model/get_global_cdn_instance_list_response.py
ncloud_cdn/model/get_global_cdn_purge_history_list_request.py
ncloud_cdn/model/get_global_cdn_purge_history_list_response.py
ncloud_cdn/model/global_cdn_instance.py
ncloud_cdn/model/global_cdn_purge_history.py
ncloud_cdn/model/global_cdn_rule.py
ncloud_cdn/model/global_cdn_service_domain.py
ncloud_cdn/model/request_cdn_plus_purge_request.py
ncloud_cdn/model/request_cdn_plus_purge_response.py
ncloud_cdn/model/request_global_cdn_purge_request.py
ncloud_cdn/model/request_global_cdn_purge_response.py
test/__init__.py
test/test_v2_api.py
ncloud_cdn-1.1.1.dist-info/LICENSE
ncloud_cdn-1.1.1.dist-info/METADATA
ncloud_cdn-1.1.1.dist-info/WHEEL
ncloud_cdn-1.1.1.dist-info/top_level.txt
ncloud_cdn-1.1.1.dist-info/RECORD
