Metadata-Version: 1.0
Name: ncloud-cdn
Version: 1.1.1
Summary: cdn
Home-page: UNKNOWN
Author: UNKNOWN
Author-email: UNKNOWN
License: UNKNOWN
Keywords: cdn
Platform: UNKNOWN
